{
  "id": "1488682",
  "name": "PT 小程序",
  "font_family": "iconfont",
  "css_prefix_text": "icon",
  "description": "",
  "glyphs": [
    {
      "icon_id": "2147307",
      "name": "投诉",
      "font_class": "tousu",
      "unicode": "e82d",
      "unicode_decimal": 59437
    },
    {
      "icon_id": "2854287",
      "name": "账单",
      "font_class": "zhangdan",
      "unicode": "e63c",
      "unicode_decimal": 58940
    },
    {
      "icon_id": "3078822",
      "name": "预约",
      "font_class": "yuyue",
      "unicode": "e600",
      "unicode_decimal": 58880
    },
    {
      "icon_id": "5964449",
      "name": "诊疗记录",
      "font_class": "health_-report-me",
      "unicode": "e60b",
      "unicode_decimal": 58891
    },
    {
      "icon_id": "5994097",
      "name": "moon",
      "font_class": "moon",
      "unicode": "e640",
      "unicode_decimal": 58944
    },
    {
      "icon_id": "6253972",
      "name": "我的会员卡",
      "font_class": "wodehuiyuanqia",
      "unicode": "e619",
      "unicode_decimal": 58905
    },
    {
      "icon_id": "6793778",
      "name": "预约",
      "font_class": "yuyue1",
      "unicode": "e606",
      "unicode_decimal": 58886
    },
    {
      "icon_id": "7213010",
      "name": "Sun",
      "font_class": "Sun",
      "unicode": "e660",
      "unicode_decimal": 58976
    },
    {
      "icon_id": "8127578",
      "name": "诊疗记录",
      "font_class": "medical",
      "unicode": "e61a",
      "unicode_decimal": 58906
    },
    {
      "icon_id": "9439450",
      "name": "服务评价-客服",
      "font_class": "kefu1",
      "unicode": "e603",
      "unicode_decimal": 58883
    },
    {
      "icon_id": "9561329",
      "name": "预约",
      "font_class": "yuyue2",
      "unicode": "e665",
      "unicode_decimal": 58981
    },
    {
      "icon_id": "10123325",
      "name": "患者端-诊疗方案",
      "font_class": "huanzheduan-zhenliaofangan",
      "unicode": "e604",
      "unicode_decimal": 58884
    }
  ]
}
